clss/VERSION
clss/__init__.py
clss/a1syntax.py
clss/auth.py
clss/cli.py
clss/drive.py
clss/jsdict.py
clss/meta.py
clss/sheets.py
clss/sysdirs.py
clss-0.2.0.dist-info/METADATA
clss-0.2.0.dist-info/WHEEL
clss-0.2.0.dist-info/entry_points.txt
clss-0.2.0.dist-info/top_level.txt
clss-0.2.0.dist-info/RECORD
