Metadata-Version: 2.1
Name: clss
Version: 0.2.0
Summary: Command-line utility for syncing with Google Sheets
Home-page: https://gitlab.com/franksh/clss/
Author: Frank S. Hestvik
Author-email: tristesse@gmail.com
License: MIT
Keywords: google-api,spreadsheets,sheets,google,api
Platform: UNKNOWN
Classifier: Development Status :: 3 - Alpha
Classifier: License :: OSI Approved :: MIT License
Classifier: Environment :: Console
Classifier: Programming Language :: Python
Classifier: Programming Language :: Python :: 3
Requires-Python: >=3.7
Requires-Dist: google-api-python-client (==2.*)
Requires-Dist: google-auth-httplib2 (==0.1.*)
Requires-Dist: google-auth-oauthlib (==0.4.*)
Requires-Dist: click
